{
    "bodies":{
        "stars":[
            {
                "pos": [800, 400],
                "vel": [0, 0.005],
                "radius": 40,
                "mass": 100000,

                "color": [200, 200, 200],
                "flair-color": [15, 13, 27],
                "flair-amount": 100,
                "flair-range": 40
            },
            {
                "pos": [10000, 3000],
                "vel": [0, -0.2],
                "radius": 30,
                "mass": 40000,

                "color": [200, 200, 200],
                "flair-color": [40, 20, 40],
                "flair-amount": 100,
                "flair-range": 40
            },
            {
                "pos": [7000, 3000],
                "vel": [0, 0.2],
                "radius": 20,
                "mass": 30000,

                "color": [200, 200, 200],
                "flair-color": [50, 20, 10],
                "flair-amount": 100,
                "flair-range": 20
            }
        ],
        "planets":[
            {
                "pos": [500, 400],
                "vel": [0, -2],
                "radius": 5,
                "mass": 1000
            },
            {
                "pos": [520, 400],
                "vel": [0, -2.8],
                "radius": 5,
                "mass": 0
            }
        ]
    }
}